README.txt
setup.py
kend/__init__.py
kend/client.py
kend/log.py
kend/model.py
kend.egg-info/PKG-INFO
kend.egg-info/SOURCES.txt
kend.egg-info/dependency_links.txt
kend.egg-info/requires.txt
kend.egg-info/top_level.txt
kend/converter/JSON.py
kend/converter/XML.py
kend/converter/__init__.py
kend/converter/base.py