Metadata-Version: 1.1
Name: kend
Version: 0.7.1
Summary: Client package for interacting with the Utopia kend server
Home-page: UNKNOWN
Author: David Thorne
Author-email: davethorne@gmail.com
License: GPLv3+
Platform: UNKNOWN
Classifier: Development Status :: 5 - Production/Stable
Classifier: Intended Audience :: Developers
Classifier: License :: OSI Approved :: GNU General Public License v3 or later (GPLv3+)
Classifier: Programming Language :: Python :: 2.7
